{
    "resourceLogs":[
       {
          "resource":{
             "attributes":[
                {
                   "key":"service.name",
                   "value":{
                      "stringValue":"otel-dotnet"
                   }
                },
                {
                   "key":"service.instance.id",
                   "value":{
                      "stringValue":"933c049b-1f18-4dbf-bd4f-acd9cbc3a03e"
                   }
                },
                {
                   "key":"telemetry.sdk.name",
                   "value":{
                      "stringValue":"opentelemetry"
                   }
                },
                {
                   "key":"telemetry.sdk.language",
                   "value":{
                      "stringValue":"dotnet"
                   }
                },
                {
                   "key":"telemetry.sdk.version",
                   "value":{
                      "stringValue":"1.6.0"
                   }
                }
             ]
          },
          "scopeLogs":[
             {
                "scope":{
                   
                },
                "logRecords":[
                   {
                      "timeUnixNano":"1698069643739368000",
                      "severityNumber":"SEVERITY_NUMBER_INFO",
                      "severityText":"Information",
                      "body":{
                         "stringValue":"Application is shutting down..."
                      },
                      "traceId":"",
                      "spanId":"",
                      "observedTimeUnixNano":"1698069643739368000"
                   }
                ]
             }
          ]
       }
    ]
 }